drlinfluids/__init__.py
drlinfluids/environments/__init__.py
drlinfluids/environments/gym.py
drlinfluids/environments/tensorforce.py
drlinfluids/environments/tianshou.py
drlinfluids/extractor.py
drlinfluids/logger.py
drlinfluids/resources/CleanFunctions
drlinfluids/resources/__init__.py
drlinfluids/runner.py
drlinfluids/trainer/__init__.py
drlinfluids/utils.py
drlinfluids/wrapper.py
drlinfluids-0.1.0.dist-info/LICENSE
drlinfluids-0.1.0.dist-info/WHEEL
drlinfluids-0.1.0.dist-info/METADATA
drlinfluids-0.1.0.dist-info/RECORD
