Metadata-Version: 2.1
Name: drlinfluids
Version: 0.1.0
Summary: A flexible platform to utilize Deep Reinforcement Learning in the field of Computational Fluid Dynamics.
License: Apache-2.0
Author: Qiulei Wang et al.
Requires-Python: >=3.8,<3.11
Classifier: License :: OSI Approved :: Apache Software License
Classifier: Programming Language :: Python :: 3
Classifier: Programming Language :: Python :: 3.10
Classifier: Programming Language :: Python :: 3.8
Classifier: Programming Language :: Python :: 3.9
Requires-Dist: PeakUtils (>=1.3.3)
Requires-Dist: numpy (>=1.18.5)
Requires-Dist: pandas (>=1.3.3)
Requires-Dist: scipy (>=1.4.1)
Requires-Dist: sympy (>=1.10.1)
Requires-Dist: tensorforce (==0.6.0)
